LICENSE
MANIFEST.in
README.md
setup.py
ud2pos
ud2pos/__init__.py
ud2pos/ud2pos.py
ud2pos.egg-info/PKG-INFO
ud2pos.egg-info/SOURCES.txt
ud2pos.egg-info/dependency_links.txt
ud2pos.egg-info/not-zip-safe
ud2pos.egg-info/top_level.txt
ud2pos/data/english-ud_lemmas.tsv
ud2pos/data/finnish-ud_lemmas.tsv
ud2pos/data/hebrew-ud_lemmas.tsv
ud2pos/data/hungarian-ud_lemmas.tsv
ud2pos/data/indonesian-ud_lemmas.tsv
ud2pos/data/marathi-ud_lemmas.tsv
ud2pos/data/portuguese-ud_lemmas.tsv
ud2pos/data/tamil-ud_lemmas.tsv
ud2pos/data/turkish-ud_lemmas.tsv