Metadata-Version: 2.1
Name: ud2pos
Version: 0.114
Summary: Method to get part-of-speech tags from universal dependencies data.
Home-page: https://github.com/tpimentelms/ud2pos
Author: Tiago Pimentel
Author-email: tpimentelms@gmail.com
License: MIT
Keywords: part-of-speech universal-dependencies
Platform: UNKNOWN
License-File: LICENSE
